peewee_momoko.py
setup.py
peewee_momoko.egg-info/PKG-INFO
peewee_momoko.egg-info/SOURCES.txt
peewee_momoko.egg-info/dependency_links.txt
peewee_momoko.egg-info/requires.txt
peewee_momoko.egg-info/top_level.txt