Metadata-Version: 1.1
Name: peewee-momoko
Version: 0.1.0
Summary: 
